fastapi_project_generator/__init__.py
fastapi_project_generator/cli.py
fastapi_project_generator/templates/.env
fastapi_project_generator/templates/.gitattributes
fastapi_project_generator/templates/.gitignore
fastapi_project_generator/templates/README.md
fastapi_project_generator/templates/requirements.txt
fastapi_project_generator/templates/app/__init__.py
fastapi_project_generator/templates/app/main.py
fastapi_project_generator/templates/app/core/__init__.py
fastapi_project_generator/templates/app/core/config.py
fastapi_project_generator/templates/app/db/__init__.py
fastapi_project_generator/templates/app/db/base.py
fastapi_project_generator/templates/app/db/session.py
fastapi_project_generator/templates/app/dependencies/__init__.py
fastapi_project_generator/templates/app/dependencies/auth.py
fastapi_project_generator/templates/app/dependencies/get_db.py
fastapi_project_generator/templates/app/models/__init__.py
fastapi_project_generator/templates/app/models/user.py
fastapi_project_generator/templates/app/routers/__init__.py
fastapi_project_generator/templates/app/routers/users.py
fastapi_project_generator/templates/app/schemas/__init__.py
fastapi_project_generator/templates/app/schemas/user.py
fastapi_project_generator/templates/app/tests/__init__.py
fastapi_project_generator/templates/app/tests/test_main.py
fastapi_project_generator/templates/app/utils/__init__.py
fastapi_project_generator/templates/app/utils/helpers.py
fastapi_project_generator-0.1.4.dist-info/METADATA
fastapi_project_generator-0.1.4.dist-info/WHEEL
fastapi_project_generator-0.1.4.dist-info/entry_points.txt
fastapi_project_generator-0.1.4.dist-info/top_level.txt
fastapi_project_generator-0.1.4.dist-info/RECORD
